dbrep/__init__.py
dbrep/cli.py
dbrep/config.py
dbrep/conversions/__init__.py
dbrep/conversions/base.py
dbrep/conversions/json_row.py
dbrep/engines/__init__.py
dbrep/engines/engine_base.py
dbrep/engines/engine_dbapi.py
dbrep/engines/engine_pgcopy.py
dbrep/engines/engine_sqlalchemy.py
dbrep/engines/experimental/kafka.py
dbrep/replication.py
dbrep/utils.py
dbrep-0.0.12.dist-info/entry_points.txt
dbrep-0.0.12.dist-info/LICENSE
dbrep-0.0.12.dist-info/WHEEL
dbrep-0.0.12.dist-info/METADATA
dbrep-0.0.12.dist-info/RECORD
