Metadata-Version: 2.1
Name: dbrep
Version: 0.0.12
Summary: Package to sync tables across DBs, i.e. EL in ELT/ETL
Author: Valentin  Stepanovich
Author-email: kolhizin@gmail.com
Requires-Python: >=3.8
Classifier: Programming Language :: Python :: 3
Classifier: Programming Language :: Python :: 3.8
Classifier: Programming Language :: Python :: 3.9
Classifier: Programming Language :: Python :: 3.10
Requires-Dist: PyYAML (>=5.0)
Requires-Dist: SQLAlchemy (>=1.4.40,<2.0.0)
Requires-Dist: cryptography (>=37.0.4,<38.0.0)
